qobuzzz_dl/__init__.py
qobuzzz_dl/download.py
qobuzzz_dl/enum.py
qobuzzz_dl/model.py
qobuzzz_dl/printf.py
qobuzzz_dl/qobuz.py
qobuzzz_dl/settings.py
qobuzzz_dl/lang/__init__.py
qobuzzz_dl/lang/arabic.py
qobuzzz_dl/lang/chinese.py
qobuzzz_dl/lang/croatian.py
qobuzzz_dl/lang/czech.py
qobuzzz_dl/lang/english.py
qobuzzz_dl/lang/filipino.py
qobuzzz_dl/lang/french.py
qobuzzz_dl/lang/german.py
qobuzzz_dl/lang/italian.py
qobuzzz_dl/lang/language.py
qobuzzz_dl/lang/portuguese.py
qobuzzz_dl/lang/russian.py
qobuzzz_dl/lang/spanish.py
qobuzzz_dl/lang/turkish.py
qobuzzz_dl/lang/ukrainian.py
qobuzzz_dl/lang/vietnamese.py
qobuzzz_dl-2021.3.25.0.dist-info/METADATA
qobuzzz_dl-2021.3.25.0.dist-info/WHEEL
qobuzzz_dl-2021.3.25.0.dist-info/entry_points.txt
qobuzzz_dl-2021.3.25.0.dist-info/top_level.txt
qobuzzz_dl-2021.3.25.0.dist-info/RECORD
