Metadata-Version: 2.1
Name: qobuzzz-dl
Version: 2021.3.25.0
Summary: Qobuz Music Downloader.
Home-page: UNKNOWN
Author: YaronH
Author-email: yaronhuang@foxmail.com
License: Apache2
Platform: any
Requires-Dist: aigpy (>=2021.3.25.1)
Requires-Dist: requests (>=2.22.0)
Requires-Dist: pycryptodome
Requires-Dist: pydub
Requires-Dist: prettytable
